<?xml version="1.0" encoding="UTF-8"?>
<!--Written on Wed Jun 26 15:22:38 2019 by Qt Creator 4.11.0-beta1 (4.10.82)-->
<externaltool id="Terminator">
    <description>Run terminator shell</description>
    <displayname>Terminator</displayname>
    <category>Text</category>
    <executable output="showinpane" error="showinpane" modifiesdocument="no">
        <path>terminator</path>
        <arguments>-f</arguments>
        <workingdirectory>%{CurrentProject:Path}</workingdirectory>
    </executable>
</externaltool>
